sos_xeus_cling/__init__.py
sos_xeus_cling/_version.py
sos_xeus_cling/kernel.py
sos_xeus_cling/utils.hpp
sos_xeus_cling-0.1.0.dist-info/LICENSE
sos_xeus_cling-0.1.0.dist-info/METADATA
sos_xeus_cling-0.1.0.dist-info/WHEEL
sos_xeus_cling-0.1.0.dist-info/entry_points.txt
sos_xeus_cling-0.1.0.dist-info/top_level.txt
sos_xeus_cling-0.1.0.dist-info/RECORD
