Metadata-Version: 2.1
Name: sos-xeus-cling
Version: 0.1.0
Summary: SoS Notebook extension for C++
Home-page: https://github.com/ktaletsk
Author: Konstantin Taletskiy
Author-email: konstantin.taletskiy@axleinfo.com
Maintainer: Konstantin Taletskiy
Maintainer-email: konstantin.taletskiy@axleinfo.com
License: MIT
Platform: UNKNOWN
Classifier: Development Status :: 4 - Beta
Classifier: Environment :: Console
Classifier: License :: OSI Approved :: MIT License
Classifier: Natural Language :: English
Classifier: Operating System :: POSIX :: Linux
Classifier: Operating System :: MacOS :: MacOS X
Classifier: Operating System :: Microsoft :: Windows
Classifier: Intended Audience :: Information Technology
Classifier: Intended Audience :: Science/Research
Classifier: Programming Language :: Python :: 3 :: Only
Classifier: Programming Language :: Python :: Implementation :: CPython
Requires-Dist: sos (>=0.18.0)
Requires-Dist: sos-notebook (>=0.18.0)
